min_distance/__init__.py
min_distance/min_distance.py
min_distance-1.0.1.dist-info/licenses/LICENSE
min_distance-1.0.1.dist-info/METADATA
min_distance-1.0.1.dist-info/WHEEL
min_distance-1.0.1.dist-info/top_level.txt
min_distance-1.0.1.dist-info/RECORD
