Metadata-Version: 2.4
Name: min_distance
Version: 1.0.1
Summary: A simple Python package to calculate the minimum distance between two geographic points
Home-page: https://github.com/vanshbhardwajhere/min_distance
Author: Vansh
Author-email: vanshbhardwajhere@gmail.com
Classifier: Programming Language :: Python :: 3
Classifier: Operating System :: OS Independent
Requires-Python: >=3.6
License-File: LICENSE
Dynamic: author
Dynamic: author-email
Dynamic: classifier
Dynamic: description
Dynamic: description-content-type
Dynamic: home-page
Dynamic: license-file
Dynamic: requires-python
Dynamic: summary
